fit_growth_mcp_tools/__init__.py
fit_growth_mcp_tools/__main__.py
fit_growth_mcp_tools-0.1.8.dist-info/WHEEL
fit_growth_mcp_tools-0.1.8.dist-info/entry_points.txt
fit_growth_mcp_tools-0.1.8.dist-info/METADATA
fit_growth_mcp_tools-0.1.8.dist-info/RECORD
