Metadata-Version: 2.3
Name: fit-growth-mcp-tools
Version: 0.1.8
Summary: Add your description here
Requires-Dist: requests>=2.32.4
Requires-Python: >=3.7
